threefiner/__init__.py
threefiner/cli.py
threefiner/gui.py
threefiner/nn.py
threefiner/opt.py
threefiner/guidance/__init__.py
threefiner/guidance/if2_ism_utils.py
threefiner/guidance/if2_nfsd_utils.py
threefiner/guidance/if2_utils.py
threefiner/guidance/if_utils.py
threefiner/guidance/sd_ism_utils.py
threefiner/guidance/sd_nfsd_utils.py
threefiner/guidance/sd_utils.py
threefiner/guidance/sdcn_utils.py
threefiner/lights/LICENSE.txt
threefiner/lights/bsdf_256_256.bin
threefiner/lights/mud_road_puresky_1k.hdr
threefiner/renderer/__init__.py
threefiner/renderer/diffmc_renderer.py
threefiner/renderer/mesh_renderer.py
threefiner/renderer/pbr_diffmc_renderer.py
threefiner/renderer/pbr_mesh_renderer.py
threefiner-0.1.2.dist-info/LICENSE
threefiner-0.1.2.dist-info/METADATA
threefiner-0.1.2.dist-info/WHEEL
threefiner-0.1.2.dist-info/entry_points.txt
threefiner-0.1.2.dist-info/top_level.txt
threefiner-0.1.2.dist-info/RECORD
