Metadata-Version: 2.1
Name: threefiner
Version: 0.1.2
Summary: Threefiner: a text-guided mesh refiner
Home-page: https://github.com/3DTopia/threefiner
Author: kiui
Author-email: ashawkey1999@gmail.com
License: MIT
Keywords: generative mesh refinement
Classifier: Topic :: Scientific/Engineering :: Artificial Intelligence
Classifier: License :: OSI Approved :: MIT License
Classifier: Programming Language :: Python :: 3
License-File: LICENSE
Requires-Dist: tyro
Requires-Dist: tqdm
Requires-Dist: rich
Requires-Dist: ninja
Requires-Dist: numpy
Requires-Dist: pandas
Requires-Dist: matplotlib
Requires-Dist: opencv-python
Requires-Dist: imageio
Requires-Dist: imageio-ffmpeg
Requires-Dist: scipy
Requires-Dist: scikit-learn
Requires-Dist: torch
Requires-Dist: einops
Requires-Dist: huggingface-hub
Requires-Dist: diffusers
Requires-Dist: accelerate
Requires-Dist: transformers
Requires-Dist: sentencepiece
Requires-Dist: plyfile
Requires-Dist: pygltflib
Requires-Dist: xatlas
Requires-Dist: trimesh
Requires-Dist: PyMCubes
Requires-Dist: pymeshlab
Requires-Dist: pysdf
Requires-Dist: diso
Requires-Dist: envlight
Requires-Dist: dearpygui
Requires-Dist: kiui >=0.2.1
